README.md
setup.py
vdr_tools.egg-info/PKG-INFO
vdr_tools.egg-info/SOURCES.txt
vdr_tools.egg-info/dependency_links.txt
vdr_tools.egg-info/requires.txt
vdr_tools.egg-info/top_level.txt
vdrtools/__init__.py
vdrtools/anoncreds.py
vdrtools/blob_storage.py
vdrtools/cache.py
vdrtools/cheqd_keys.py
vdrtools/cheqd_pool.py
vdrtools/crypto.py
vdrtools/did.py
vdrtools/error.py
vdrtools/ledger.py
vdrtools/libindy.py
vdrtools/non_secrets.py
vdrtools/pairwise.py
vdrtools/pool.py
vdrtools/vdr.py
vdrtools/version.py
vdrtools/wallet.py
vdrtools/cheqd_ledger/__init__.py
vdrtools/cheqd_ledger/auth.py
vdrtools/cheqd_ledger/bank.py
vdrtools/cheqd_ledger/cheqd.py
vdrtools/cheqd_ledger/tx.py