Metadata-Version: 2.1
Name: vdr-tools
Version: 0.8.4
Summary: A library that facilitates building standards compliant and interoperable solutions for self-sovereign identity by abstracting the operations for interacting with a verifiable data registry as defined by Hyperledger Aries.
Home-page: https://github.com/evernym/vdr-tools
Author: Evernym
Author-email: dev@evernym.com
License: Apache-2.0
Platform: UNKNOWN
Provides-Extra: test
